{
  "$schema": "https://ui.shadcn.com/schema/registry-item.json",
  "name": "android-demo",
  "type": "registry:component",
  "registryDependencies": [
    "android"
  ],
  "files": [
    {
      "path": "registry/example/android-demo.tsx",
      "content": "import Android from \"@/registry/magicui/android\";\n\nexport default function AndroidDemo() {\n  return (\n    <div className=\"relative\">\n      <Android className=\"size-full\" />\n    </div>\n  );\n}\n",
      "type": "registry:component"
    }
  ]
}